vxpipeline/__init__.py
vxpipeline/conect.py
vxpipeline/extract.py
vxpipeline/load.py
vxpipeline/transform.py
vxpipeline-0.2.0.dist-info/METADATA
vxpipeline-0.2.0.dist-info/WHEEL
vxpipeline-0.2.0.dist-info/top_level.txt
vxpipeline-0.2.0.dist-info/RECORD
