Metadata-Version: 2.4
Name: vxpipeline
Version: 0.2.0
Summary: Add your description here
Requires-Python: >=3.10
Requires-Dist: awswrangler>=3.11.0
Requires-Dist: boto3>=1.37.24
Requires-Dist: ipykernel>=6.29.5
Requires-Dist: numpy>=2.2.4
Requires-Dist: openpyxl>=3.1.5
Requires-Dist: pandas>=2.2.3
Requires-Dist: pip>=25.0.1
Requires-Dist: psycopg2>=2.9.10
Requires-Dist: pymongo>=4.11.3
Requires-Dist: pyodbc>=5.2.0
Requires-Dist: pytz>=2025.2
Requires-Dist: setuptools>=78.1.0
Requires-Dist: twine>=6.1.0
Requires-Dist: wheel>=0.45.1
